[
  {
    "number": 61,
    "topic": "How to Build a Sustainable Morning Skincare Routine",
    "maxWords": 2500,
    "useImage": {
      "use": true,
      "TotalImagesToBeUsed": 2,
      "searchQueryForImages": [
        "skincare routine",
        "natural skincare"
      ]
    },
    "useCharts": {
      "use": false,
      "TotalChartsToBeUsed": 0
    },
    "usePreviewCode": {
      "use": false,
      "Total": 0,
      "previewType": [],
      "languages": []
    },
    "useTable": {
      "use": true,
      "TotalTablesToBeUsed": 1
    },
    "language": "English",
    "targetAudience": [
      "beauty enthusiasts",
      "general public",
      "young adults"
    ],
    "difficultyLevel": "Beginner",
    "category": "Day-to-Day Life",
    "targetRegion": "Global"
  },
  {
    "number": 62,
    "topic": "The Role of Blockchain in Supply Chain Transparency",
    "maxWords": 3200,
    "useImage": {
      "use": true,
      "TotalImagesToBeUsed": 3,
      "searchQueryForImages": [
        "blockchain supply chain",
        "supply chain transparency",
        "decentralized logistics"
      ]
    },
    "useCharts": {
      "use": true,
      "TotalChartsToBeUsed": 2
    },
    "usePreviewCode": {
      "use": true,
      "Total": 1,
      "previewType": [
        "code"
      ],
      "languages": [
        "JavaScript"
      ]
    },
    "useTable": {
      "use": true,
      "TotalTablesToBeUsed": 1
    },
    "language": "English",
    "targetAudience": [
      "business professionals",
      "tech enthusiasts",
      "logistics experts"
    ],
    "difficultyLevel": "Advanced",
    "category": "Technology",
    "targetRegion": "Europe"
  },
  {
    "number": 63,
    "topic": "The Benefits of Learning a New Language as an Adult",
    "maxWords": 2600,
    "useImage": {
      "use": true,
      "TotalImagesToBeUsed": 2,
      "searchQueryForImages": [
        "language learning",
        "adult education"
      ]
    },
    "useCharts": {
      "use": false,
      "TotalChartsToBeUsed": 0
    },
    "usePreviewCode": {
      "use": false,
      "Total": 0,
      "previewType": [],
      "languages": []
    },
    "useTable": {
      "use": true,
      "TotalTablesToBeUsed": 1
    },
    "language": "English",
    "targetAudience": [
      "general public",
      "professionals",
      "students"
    ],
    "difficultyLevel": "Intermediate",
    "category": "Day-to-Day Life",
    "targetRegion": "US"
  },
  {
    "number": 64,
    "topic": "The Impact of Edge AI on Real-Time Data Processing",
    "maxWords": 3100,
    "useImage": {
      "use": true,
      "TotalImagesToBeUsed": 3,
      "searchQueryForImages": [
        "edge AI",
        "real-time data",
        "AI processing"
      ]
    },
    "useCharts": {
      "use": true,
      "TotalChartsToBeUsed": 2
    },
    "usePreviewCode": {
      "use": true,
      "Total": 1,
      "previewType": [
        "code"
      ],
      "languages": [
        "Python"
      ]
    },
    "useTable": {
      "use": true,
      "TotalTablesToBeUsed": 1
    },
    "language": "English",
    "targetAudience": [
      "tech enthusiasts",
      "developers",
      "data scientists"
    ],
    "difficultyLevel": "Advanced",
    "category": "Technology",
    "targetRegion": "India"
  },
  {
    "number": 65,
    "topic": "How to Create a Productive Home Office Space",
    "maxWords": 2700,
    "useImage": {
      "use": true,
      "TotalImagesToBeUsed": 2,
      "searchQueryForImages": [
        "home office",
        "workspace design"
      ]
    },
    "useCharts": {
      "use": false,
      "TotalChartsToBeUsed": 0
    },
    "usePreviewCode": {
      "use": false,
      "Total": 0,
      "previewType": [],
      "languages": []
    },
    "useTable": {
      "use": true,
      "TotalTablesToBeUsed": 1
    },
    "language": "English",
    "targetAudience": [
      "remote workers",
      "freelancers",
      "professionals"
    ],
    "difficultyLevel": "Intermediate",
    "category": "Day-to-Day Life",
    "targetRegion": "Europe"
  },
  {
    "number": 66,
    "topic": "The Global Impact of Renewable Energy Adoption",
    "maxWords": 2800,
    "useImage": {
      "use": true,
      "TotalImagesToBeUsed": 3,
      "searchQueryForImages": [
        "renewable energy",
        "solar energy",
        "wind power"
      ]
    },
    "useCharts": {
      "use": false,
      "TotalChartsToBeUsed": 0
    },
    "usePreviewCode": {
      "use": false,
      "Total": 0,
      "previewType": [],
      "languages": []
    },
    "useTable": {
      "use": true,
      "TotalTablesToBeUsed": 1
    },
    "language": "English",
    "targetAudience": [
      "environmentalists",
      "general public",
      "policy makers"
    ],
    "difficultyLevel": "Intermediate",
    "category": "General",
    "targetRegion": "Global"
  },
  {
    "number": 67,
    "topic": "The Future of Personalized Medicine with AI",
    "maxWords": 3000,
    "useImage": {
      "use": true,
      "TotalImagesToBeUsed": 3,
      "searchQueryForImages": [
        "personalized medicine",
        "AI healthcare",
        "medical technology"
      ]
    },
    "useCharts": {
      "use": true,
      "TotalChartsToBeUsed": 2
    },
    "usePreviewCode": {
      "use": true,
      "Total": 1,
      "previewType": [
        "code"
      ],
      "languages": [
        "Python"
      ]
    },
    "useTable": {
      "use": true,
      "TotalTablesToBeUsed": 1
    },
    "language": "English",
    "targetAudience": [
      "healthcare professionals",
      "tech enthusiasts",
      "researchers"
    ],
    "difficultyLevel": "Advanced",
    "category": "Technology",
    "targetRegion": "US"
  },
  {
    "number": 68,
    "topic": "The Joy of Gardening: Tips for Beginners",
    "maxWords": 2600,
    "useImage": {
      "use": true,
      "TotalImagesToBeUsed": 2,
      "searchQueryForImages": [
        "beginner gardening",
        "home garden"
      ]
    },
    "useCharts": {
      "use": false,
      "TotalChartsToBeUsed": 0
    },
    "usePreviewCode": {
      "use": false,
      "Total": 0,
      "previewType": [],
      "languages": []
    },
    "useTable": {
      "use": true,
      "TotalTablesToBeUsed": 1
    },
    "language": "English",
    "targetAudience": [
      "gardeners",
      "homeowners",
      "general public"
    ],
    "difficultyLevel": "Beginner",
    "category": "Day-to-Day Life",
    "targetRegion": "India"
  },
  {
    "number": 69,
    "topic": "The Role of Storytelling in Building Strong Communities",
    "maxWords": 2700,
    "useImage": {
      "use": true,
      "TotalImagesToBeUsed": 2,
      "searchQueryForImages": [
        "community storytelling",
        "cultural narratives"
      ]
    },
    "useCharts": {
      "use": false,
      "TotalChartsToBeUsed": 0
    },
    "usePreviewCode": {
      "use": false,
      "Total": 0,
      "previewType": [],
      "languages": []
    },
    "useTable": {
      "use": true,
      "TotalTablesToBeUsed": 1
    },
    "language": "English",
    "targetAudience": [
      "community leaders",
      "general public",
      "culture enthusiasts"
    ],
    "difficultyLevel": "Intermediate",
    "category": "General",
    "targetRegion": "Global"
  },
  {
    "number": 70,
    "topic": "The Impact of Quantum Cryptography on Data Security",
    "maxWords": 3100,
    "useImage": {
      "use": true,
      "TotalImagesToBeUsed": 3,
      "searchQueryForImages": [
        "quantum cryptography",
        "data security",
        "quantum technology"
      ]
    },
    "useCharts": {
      "use": true,
      "TotalChartsToBeUsed": 2
    },
    "usePreviewCode": {
      "use": true,
      "Total": 1,
      "previewType": [
        "code"
      ],
      "languages": [
        "Python"
      ]
    },
    "useTable": {
      "use": true,
      "TotalTablesToBeUsed": 1
    },
    "language": "English",
    "targetAudience": [
      "security professionals",
      "tech enthusiasts",
      "researchers"
    ],
    "difficultyLevel": "Advanced",
    "category": "Technology",
    "targetRegion": "Europe"
  }
]